sca_logger/__init__.py
sca_logger/sanitize.py
sca_logger/sca_formatter.py
sca_logger/sca_log_filter.py
sca_logger/sca_memory_handler.py
sca_logger/sca_structured_log.py
sca_logger/utils.py
sca_logger_python-2.2.8.dist-info/METADATA
sca_logger_python-2.2.8.dist-info/WHEEL
sca_logger_python-2.2.8.dist-info/top_level.txt
sca_logger_python-2.2.8.dist-info/RECORD
