Metadata-Version: 2.1
Name: sca_logger_python
Version: 2.2.8
Summary: Provides a logger client, more specific to work with AWS Lambda and log to Kinesis
Author: Venkatesh Kara
Author-email: vkara@tesla.com
Classifier: Programming Language :: Python :: 3.6
Classifier: Programming Language :: Python :: 3.7
Classifier: Programming Language :: Python :: 3.8
Classifier: Programming Language :: Python :: 3.9
